{ "datum":"02.10.2022","rueden":1,"huendinnen":1,"vater":"Ch. Füchslein Fünf o'the Palatinate Pixies","mutter":"Half a Jiffy o'the Palatinate Pixies","name":"Born to Make you Smile","zuechter":"Isabel Voigt" };{ "datum":"23.02.2023","rueden":0,"huendinnen":2,"vater":"Ch. Heavenli Lab Vincent For Massenbachtal","mutter":"Ch. Siggen’s J J Janis Joplin","name":"vonne Daggelküste","zuechter":"Gaby Hauber" };{ "datum":"28.07.2024","rueden":2,"huendinnen":3,"vater":"Karat Iz Byrshtnovogo Kraju","mutter":"Davina Of The Jolly Jumpers","name":"Dourin's","zuechter":"Rina Grouwstra" };{ "datum":"01.08.2023","rueden":4,"huendinnen":1,"vater":"Ch. Percy Iz Doma Vengee","mutter":"Jaffa von Kirchhellen","name":"von Kirchhellen","zuechter":"Johannes" };{ "datum":"06.04.2022","rueden":2,"huendinnen":5,"vater":"Ch. Lagrein Alto Adige Iz Angarii","mutter":"Treasure Dream Boleo","name":"from black riding Hood","zuechter":"Claudia Bohne" };{ "datum":"10.09.2024","rueden":3,"huendinnen":1,"vater":"Ch. Poem of Love to Sweet Mochi vom Kalimandscharo","mutter":"Trouble Trulla Cersei vom Kalimandscharo","name":"vom Kalimandscharo","zuechter":"Nancy Leetz" };{ "datum":"25.11.2021","rueden":1,"huendinnen":0,"vater":"Kalashnikhof Armani","mutter":"Academia Canis Alice","name":"von Kirchhellen","zuechter":"Johannes" };{ "datum":"23.06.2024","rueden":3,"huendinnen":2,"vater":"Ch. Victorious Attila King of Corgi vom Kalimandscharo","mutter":"Ch. Füchslein Frech o'the Palatinate Pixies","name":"von der Wertachau","zuechter":"Brigitte Stammel" };{ "datum":"23.03.2024","rueden":4,"huendinnen":3,"vater":"Ch. Victorious Attila King of Corgi vom Kalimandscharo","mutter":"Ch. Wjesha vom Old Tom","name":"vom Old Tom","zuechter":"Jolanta Vogt" };{ "datum":"12.02.2024","rueden":2,"huendinnen":2,"vater":"Ch. ANTOINE Des trois lis de Bourbon","mutter":"Halligalli von Pfotenstolz","name":"Des trois lis de Bourbon","zuechter":"Christine Feld" };{ "datum":"26.07.2023","rueden":3,"huendinnen":1,"vater":"Ch. Triple H Mid Knight Rumble","mutter":"Heym of Hassellyn Jumping Julia","name":"Heym of Hassellyn","zuechter":"Dr. med. Friedrich" };{ "datum":"13.07.2023","rueden":1,"huendinnen":2,"vater":"Pumuckl vom Kalimandscharo","mutter":"Guess Nova Irlandia","name":"Ellylldan","zuechter":"Pia Immoor" };{ "datum":"10.01.2022","rueden":1,"huendinnen":3,"vater":"Ch. Corwen’s Farmhouse Laycoo","mutter":"Ch. Quo Vadis Rosie","name":"Quo Vadis","zuechter":"Lilo Kiel" };{ "datum":"30.10.2021","rueden":1,"huendinnen":5,"vater":"Quo Vadis Xandro BOB","mutter":"Victoria Amatoria Samanta Fox","name":"von Pfotenstolz","zuechter":"Myrjam Langen" };{ "datum":"18.12.2023","rueden":1,"huendinnen":1,"vater":"Ch. King Cosmo vom Kalimandscharo","mutter":"Ch. Amansi One Night In Summer","name":"vom Kalimandscharo","zuechter":"Nancy Leetz" };{ "datum":"28.01.2022","rueden":5,"huendinnen":1,"vater":"Honeyhouse Guess Who Is At Ryediver","mutter":"Daredevil's Rhinestone Cowgirl from Staken","name":"Daredevil's...from Staken","zuechter":"Danny Reinkehr" };{ "datum":"14.02.2024","rueden":2,"huendinnen":3,"vater":"Ch. Honeyhouse Guess Who Is At Ryediver","mutter":"Trouble Trulla Cersei vom Kalimandscharo","name":"vom Kalimandscharo","zuechter":"Nancy Leetz" };{ "datum":"19.09.2023","rueden":1,"huendinnen":2,"vater":"Ch. Richard Valiant Knight For Massenbachtal","mutter":"Ch. Felicitas Bob vom Massenbachtal","name":"vom Massenbachtal","zuechter":"Wladimir Handschuh" };{ "datum":"10.01.2024","rueden":3,"huendinnen":3,"vater":"Ch. Born To Be Glitter In The Air","mutter":"Ch. Amoretka Lisiura","name":"Bakersfield","zuechter":"Marcus Wilke" };{ "datum":"06.03.2022","rueden":1,"huendinnen":1,"vater":"Nothing Compares 2U Halo Rudens Legendos","mutter":"Ch. Daredevil's Go Gentle from Staken","name":"Daredevil's...from Staken","zuechter":"Danny Reinkehr" };{ "datum":"20.08.2024","rueden":0,"huendinnen":2,"vater":"Ch. Tamera’s Wish Upon A Star","mutter":"Elves Fairytale On Cloud Nine","name":"Life's finest","zuechter":"Karin Seidel" };{ "datum":"14.04.2023","rueden":3,"huendinnen":3,"vater":"Pumuckl vom Kalimandscharo","mutter":"Inkery Line Music Akvarele","name":"from the Pegnitzfairys","zuechter":"Ruth Schroetel" };{ "datum":"06.04.2022","rueden":1,"huendinnen":3,"vater":"Ch. Fest Upper Class","mutter":"Inkery Line Zhozefina","name":"LIVE YOUR DREAMS","zuechter":"Lorena Lell" };{ "datum":"01.03.2024","rueden":2,"huendinnen":3,"vater":"Ch. Lagrein Alto Adige Iz Angarii","mutter":"Crystal Mett from black riding Hood","name":"from black riding Hood","zuechter":"Claudia Bohne" };{ "datum":"02.08.2023","rueden":3,"huendinnen":4,"vater":"Ch. Richard Valiant Knight For Massenbachtal","mutter":"Nochnfux o'the Palatinate Pixies","name":"LIVE YOUR DREAMS","zuechter":"Lorena Lell" };{ "datum":"07.04.2023","rueden":2,"huendinnen":1,"vater":"Ch. Andvol Marius Loo","mutter":"Ch. Pemspride Double Trouble","name":"Pemspride","zuechter":"Astrid Acht" };{ "datum":"06.04.2022","rueden":4,"huendinnen":1,"vater":"Ch. Johnny I Hardly Knew Ya o'the Palatinate Pixies","mutter":"Quo Vadis Yette","name":"Telling Fairytales","zuechter":"Michaela Zimmermann" };{ "datum":"09.10.2022","rueden":1,"huendinnen":3,"vater":"Egil Ellefolk o'the Palatinate Pixies","mutter":"Just My Two Cents o'the Palatinate Pixies","name":"o'the Palatinate Pixies","zuechter":"Sabine Thomas" };{ "datum":"09.07.2022","rueden":2,"huendinnen":4,"vater":"Ch. Bart Junoba’s House","mutter":"Quo Vadis Zarah Zuckerpuppe","name":"Quo Vadis","zuechter":"Lilo Kiel" };{ "datum":"17.02.2023","rueden":1,"huendinnen":4,"vater":"Egil Ellefolk o'the Palatinate Pixies","mutter":"Etepetete von Pfotenstolz","name":"von Pfotenstolz","zuechter":"Myrjam Langen" };{ "datum":"18.04.2023","rueden":3,"huendinnen":2,"vater":"Ch. Vuedor Sky Rocket","mutter":"Quo Vadis Ustinella","name":"vom Weinbergschlösschen","zuechter":"Sebastian Schulz" };{ "datum":"26.10.2023","rueden":2,"huendinnen":3,"vater":"Ch. Victoria Amatoria Rocky My Sweet","mutter":"Uschi Unicum vom Old Tom","name":"vom Old Tom","zuechter":"Jolanta Vogt" };{ "datum":"22.02.2023","rueden":3,"huendinnen":3,"vater":"Ch. Trifecta Eagle Scout","mutter":"Ch. Daredevil's Move Like Jagger from Staken","name":"Daredevil's...from Staken","zuechter":"Danny Reinkehr" };{ "datum":"10.02.2022","rueden":1,"huendinnen":1,"vater":"Ch. Corwen’s Farmhouse Laycoo","mutter":"Quo Vadis Riecke","name":"Quo Vadis","zuechter":"Lilo Kiel" };{ "datum":"07.10.2022","rueden":1,"huendinnen":3,"vater":"Quo Vadis Xandro BOB","mutter":"Twenty Oaks Farm Ashley","name":"Twenty Oaks Farm","zuechter":"Astrid Rumprecht" };{ "datum":"16.07.2022","rueden":4,"huendinnen":6,"vater":"Amansi Sunshine For Me","mutter":"Quest of Queen Arya vom Kalimandscharo","name":"vom Kalimandscharo","zuechter":"Nancy Leetz" };{ "datum":"08.04.2024","rueden":2,"huendinnen":0,"vater":"Ch. Victorious Attila King of Corgi vom Kalimandscharo","mutter":"Ch. Born To Be Your Lunch At Cartier","name":"vom Weinbergschlösschen","zuechter":"Sebastian Schulz" };{ "datum":"20.06.2023","rueden":1,"huendinnen":5,"vater":"Ch. Cornatello Apocalypse","mutter":"Ch. Baby Little Sunshine of Jolla's Joy","name":"of the Western Saxon Highlanders","zuechter":"Dr. Berthold" };{ "datum":"21.08.2022","rueden":5,"huendinnen":4,"vater":"Ch. Daredevil's Hunting for Compliments from Staken","mutter":"Amazing Pornstar from black riding Hood","name":"from black riding Hood","zuechter":"Claudia Bohne" };{ "datum":"12.05.2022","rueden":2,"huendinnen":0,"vater":"Kingstone Iz Byrshtunovogo Kraju","mutter":"Raja von Kirchhellen","name":"von Kirchhellen","zuechter":"Johannes" };{ "datum":"19.05.2024","rueden":1,"huendinnen":1,"vater":"Ch. Tamera’s Wish Upon A Star","mutter":"Daredevil's Rhinestone Cowgirl from Staken","name":"Daredevil's...from Staken","zuechter":"Danny Reinkehr" };{ "datum":"16.03.2024","rueden":2,"huendinnen":4,"vater":"Ch. Pinkys Panther o'the Palatinate Pixies","mutter":"Twenty Oaks Farm Ashley","name":"Twenty Oaks Farm","zuechter":"Astrid Rumprecht" };{ "datum":"04.06.2023","rueden":3,"huendinnen":3,"vater":"Limbonsnest Salvador","mutter":"Dourin’s Robine Pem BOB","name":"Dourin's","zuechter":"Rina Grouwstra" };{ "datum":"18.11.2023","rueden":0,"huendinnen":2,"vater":"Ch. Andvol Skif","mutter":"Korsika Paradisu vom Massenbachtal","name":"vom Massenbachtal","zuechter":"Wladimir Handschuh" };{ "datum":"17.03.2024","rueden":5,"huendinnen":2,"vater":"Ch. Daredevil's Macho Kiwi King from Staken","mutter":"Amazing Pornstar from black riding Hood","name":"from black riding Hood","zuechter":"Claudia Bohne" };{ "datum":"21.07.2023","rueden":2,"huendinnen":1,"vater":"Ch. Victoria Amatoria Ringo Starr","mutter":"Be My Flowerbomb von Pfotenstolz","name":"von Pfotenstolz","zuechter":"Myrjam Langen" };{ "datum":"20.05.2024","rueden":4,"huendinnen":2,"vater":"Ch. Richard Valiant Knight For Massenbachtal","mutter":"Korsika Paradisu vom Massenbachtal","name":"vom Massenbachtal","zuechter":"Wladimir Handschuh" };{ "datum":"09.12.2021","rueden":3,"huendinnen":1,"vater":"Kalashnikhof Armani","mutter":"Oktavia von Kirchhellen","name":"von Kirchhellen","zuechter":"Johannes" };{ "datum":"15.06.2022","rueden":4,"huendinnen":2,"vater":"Coco Jin Across the Desert","mutter":"Poem of Love to Carrie vom Kalimandscharo","name":"vom Kalimandscharo","zuechter":"Nancy Leetz" };{ "datum":"12.10.2023","rueden":0,"huendinnen":3,"vater":"Ch. Wallfugh Just Do It","mutter":"Ch. Quo Vadis Fantastic Disney BOB","name":"vom Weinbergschlösschen","zuechter":"Sebastian Schulz" };{ "datum":"19.07.2022","rueden":4,"huendinnen":2,"vater":"Ch. Victoria Amatoria Rocky My Sweet","mutter":"Uschi Unicum vom Old Tom","name":"vom Old Tom","zuechter":"Jolanta Vogt" };{ "datum":"18.08.2023","rueden":0,"huendinnen":1,"vater":"Ch. Johnny I Hardly Knew Ya o'the Palatinate Pixies","mutter":"Quo Vadis Yette","name":"Telling Fairytales","zuechter":"Michaela Zimmermann" };{ "datum":"09.11.2023","rueden":4,"huendinnen":0,"vater":"Ch. Victorious Attila King of Corgi vom Kalimandscharo","mutter":"Minerva McGonagall vom Kalimandscharo","name":"von der Müggelspree","zuechter":"Sigrid" };{ "datum":"30.11.2023","rueden":3,"huendinnen":2,"vater":"Ch. Richard Valiant Knight For Massenbachtal","mutter":"Heavenli Lab Emblem Of Love","name":"vom Rhöner Elsbachtal","zuechter":"Nadine Englert" };{ "datum":"07.11.2023","rueden":3,"huendinnen":3,"vater":"Ch. Victorious Attila King of Corgi vom Kalimandscharo","mutter":"Zensi von Kirchhellen","name":"Queenpaws","zuechter":"Lena Gerner" };{ "datum":"19.01.2024","rueden":0,"huendinnen":4,"vater":"Ch. Arwin Corgiira Moravia","mutter":"Notorious Queenie Hermine vom Kalimandscharo","name":"vom Kalimandscharo","zuechter":"Nancy Leetz" };{ "datum":"27.05.2024","rueden":2,"huendinnen":0,"vater":"Ch. Heym of Hassellyn Jumping Joseph Bob","mutter":"Lower Saxon Born This Way","name":"Lower Saxon","zuechter":"Renate Hilger" };{ "datum":"26.02.2022","rueden":2,"huendinnen":1,"vater":"Ch. Heartbreaker Tri From Valhalos Sargas","mutter":"Zgarda vom Orthrostempel Iz Doma Na Holme","name":"vom Orthrostempel","zuechter":"Sofia Yanishevskaya" };{ "datum":"30.11.2023","rueden":3,"huendinnen":2,"vater":"Ch. Richard Valiant Knight For Massenbachtal","mutter":"Heaenli Lab Emblem Of Love","name":"vom Rhöner Elsbachtal","zuechter":"Nadine Englert" };{ "datum":"31.07.2023","rueden":4,"huendinnen":2,"vater":"Ch. Lagrein Alto Adige Iz Angarii","mutter":"Treasure Dream Boleo","name":"from black riding Hood","zuechter":"Claudia Bohne" };{ "datum":"11.11.2022","rueden":3,"huendinnen":3,"vater":"Karat I J Byrshtnovogo Kraju","mutter":"Jaffa von Kirchhellen","name":"von Kirchhellen","zuechter":"Johannes" };{ "datum":"28.12.2023","rueden":5,"huendinnen":1,"vater":"Ch. Born To Be Glitter In The Air","mutter":"Chin Chin from black riding Hood","name":"from black riding Hood","zuechter":"Claudia Bohne" };{ "datum":"11.03.2023","rueden":0,"huendinnen":1,"vater":"Ch. Daredevil's Macho Kiwi King from Staken","mutter":"Ch. Amansi One Night In Summer","name":"vom Kalimandscharo","zuechter":"Nancy Leetz" };{ "datum":"07.01.2022","rueden":4,"huendinnen":6,"vater":"Ch. Daredevil's Hunting for Compliments from Staken","mutter":"Kalashnikhof Flor De Lis","name":"from black riding Hood","zuechter":"Claudia Bohne" };{ "datum":"03.06.2022","rueden":2,"huendinnen":2,"vater":"Amansi Sunshine For Me","mutter":"Jette vom Kalimandscharo","name":"vom Kalimandscharo","zuechter":"Nancy Leetz" };{ "datum":"14.04.2023","rueden":3,"huendinnen":1,"vater":"Honeyhouse Guess Who Is At Ryediver","mutter":"Flowing The Girl In Black","name":"Daredevil's...from Staken","zuechter":"Danny Reinkehr" };{ "datum":"08.05.2022","rueden":1,"huendinnen":2,"vater":"Pumuckl vom Kalimandscharo","mutter":"Creme Brulee von Pfotenstolz","name":"vom Jubachtal","zuechter":"Matthias Schneider" };{ "datum":"07.11.2023","rueden":2,"huendinnen":3,"vater":"Ch. Percy Iz Doma Vengee","mutter":"Samoya Von Haus Vom Steraldted","name":"von Kirchhellen","zuechter":"Johannes" };{ "datum":"11.06.2024","rueden":0,"huendinnen":1,"vater":"Ch. Daredevil's Macho Kiwi King from Staken","mutter":"Etepetete von Pfotenstolz","name":"von Pfotenstolz","zuechter":"Myrjam Langen" };{ "datum":"08.05.2022","rueden":4,"huendinnen":1,"vater":"Ch. Jagger On Stage Haus Wityk","mutter":"Andvol Chelsea Flowers","name":"Pemspride","zuechter":"Astrid Acht" };{ "datum":"19.01.2023","rueden":2,"huendinnen":2,"vater":"Ch. Arwin Corgiira Moravia","mutter":"Notorious Queenie Hermine vom Kalimandscharo","name":"vom Kalimandscharo","zuechter":"Nancy Leetz" };{ "datum":"10.03.2022","rueden":2,"huendinnen":0,"vater":"Kingstone Iz Byrshtunovogo Kraju","mutter":"Merle von Haus vom Steraldted","name":"von Kirchhellen","zuechter":"Johannes" };{ "datum":"14.01.2022","rueden":4,"huendinnen":2,"vater":"Ch. Heavenli Lab Vincent For Massenbachtal","mutter":"Eowyn vom Massenbachtal","name":"vom Massenbachtal","zuechter":"Wladimir Handschuh" };{ "datum":"12.08.2023","rueden":2,"huendinnen":4,"vater":"Karat Iz Byrshtunovogo Kraju","mutter":"Corcastle Paris In Renaissance","name":"Dourin's","zuechter":"Rina Grouwstra" };{ "datum":"24.08.2024","rueden":2,"huendinnen":4,"vater":"nbird Noble Lies","mutter":"Heym of Hassellyn Jumping Josephine Bob","name":"Heym of Hassellyn","zuechter":"Dr. med. Friedrich" };{ "datum":"31.03.2022","rueden":2,"huendinnen":2,"vater":"Ch. Heartbreaker Tri From Valhalos Sargas","mutter":"Quo Vadis Tootsie BOB","name":"Quo Vadis","zuechter":"Lilo Kiel" };{ "datum":"22.04.2022","rueden":1,"huendinnen":4,"vater":"Ch. Johnny I Hardly Knew Ya o'the Palatinate Pixies","mutter":"Adele of Jolla's Joy","name":"Jolla's Joy","zuechter":"Andrea Rink" };{ "datum":"25.05.2023","rueden":0,"huendinnen":5,"vater":"Ch. Pemcader Tell It As It Is","mutter":"Ch. Just Jane Doe o'the Palatinate Pixies","name":"o'the Palatinate Pixies","zuechter":"Sabine Thomas" };{ "datum":"05.06.2022","rueden":2,"huendinnen":3,"vater":"Amansi Sunshine For Me","mutter":"Be My Flowerbomb von Pfotenstolz","name":"von Pfotenstolz","zuechter":"Myrjam Langen" };{ "datum":"05.12.2021","rueden":3,"huendinnen":1,"vater":"Honeyhouse Guess Who Is At Ryediver","mutter":"Daredevil's No Rye Too High from Staken","name":"RyeDiver","zuechter":"Gloria Kiy" };{ "datum":"26.05.2022","rueden":3,"huendinnen":1,"vater":"Ch. Vuedor Sky Rocket","mutter":"Akswell Dream Queen","name":"Oakwood Golden","zuechter":"Gebkea Nieter" };{ "datum":"20.01.2024","rueden":1,"huendinnen":5,"vater":"Ch. Johnny I Hardly Knew Ya o'the Palatinate Pixies","mutter":"Double Creek Gossip Girl","name":"o'the Palatinate Pixies","zuechter":"Sabine Thomas" };{ "datum":"26.09.2023","rueden":0,"huendinnen":1,"vater":"Ch. Andvol Marius Loo","mutter":"Ch. Pemspride BUMBLE BEE","name":"Pemspride","zuechter":"Astrid Acht" };{ "datum":"30.10.2023","rueden":0,"huendinnen":3,"vater":"Ch. Heartbreaker Tri From Valhalos Sargas","mutter":"Zgarda vom Orthrostempel Iz Doma Na Holme","name":"vom Orthrostempel","zuechter":"Sofia Yanishevskaya" };{ "datum":"26.08.2024","rueden":3,"huendinnen":4,"vater":"Ch. Tamera’s Wish Upon A Star","mutter":"Just My Two Cents o'the Palatinate Pixies","name":"o'the Palatinate Pixies","zuechter":"Sabine Thomas" };{ "datum":"11.12.2023","rueden":4,"huendinnen":6,"vater":"Ch. Y Ddraig Goch Somebody To Love","mutter":"Ch. Lower Saxon Asimbonanga","name":"Lower Saxon","zuechter":"Renate Hilger" };{ "datum":"12.01.2022","rueden":4,"huendinnen":2,"vater":"Stan von Kirchhellen","mutter":"Inkery Line Music Akvarele","name":"from the Pegnitzfairys","zuechter":"Ruth Schroetel" };{ "datum":"08.12.2022","rueden":3,"huendinnen":4,"vater":"Ch. Richard Valiant Knight For Massenbachtal","mutter":"Ch. X","name":"vom Old Tom","zuechter":"Jolanta Vogt" };{ "datum":"21.09.2022","rueden":2,"huendinnen":1,"vater":"Ch. Vuedor Sky Rocket","mutter":"Ch. Daredevil's Make Me Smile from Staken","name":"Daredevil's...from Staken","zuechter":"Danny Reinkehr" };{ "datum":"20.01.2022","rueden":2,"huendinnen":2,"vater":"Ch. Daredevil's Hunting for Compliments from Staken","mutter":"Tinatel Bristol","name":"Brightwater's","zuechter":"Nicola Bscher" };{ "datum":"01.11.2022","rueden":1,"huendinnen":0,"vater":"Coco Jin Across the Desert","mutter":"Aikemuno Gloria","name":"from the Pegnitzfairys","zuechter":"Ruth Schroetel" };{ "datum":"08.03.2023","rueden":3,"huendinnen":1,"vater":"Quo Vadis Xandro BOB","mutter":"Mistycor Flirt’N’Flash","name":"Quo Vadis","zuechter":"Lilo Kiel" };{ "datum":"28.05.2022","rueden":3,"huendinnen":1,"vater":"Ch. Logan vom Old Tom","mutter":"Ch. Wjesha vom Old Tom","name":"vom Old Tom","zuechter":"Jolanta Vogt" };{ "datum":"10.05.2024","rueden":3,"huendinnen":3,"vater":"Ch. Füchslein Fünf o'the Palatinate Pixies","mutter":"Born To Be Your Alexandrina Victoria","name":"Born to Make you Smile","zuechter":"Isabel Voigt" };{ "datum":"21.03.2024","rueden":3,"huendinnen":1,"vater":"Ch. Richard Valiant Knight For Massenbachtal","mutter":"Honey Princess Bob vom Massenbachtal","name":"of Peat County","zuechter":"Barbara Schwaiger" };{ "datum":"07.04.2024","rueden":2,"huendinnen":0,"vater":"Ch. Richard Valiant Knight For Massenbachtal","mutter":"Ch. Quality Mark Benediction Of Heavens","name":"Ellylldan","zuechter":"Pia Immoor" };{ "datum":"21.08.2024","rueden":2,"huendinnen":3,"vater":"Ch. Vuedor Sky Rocket","mutter":"Ch. Lady Sansa vom Massenbachtal","name":"vom Massenbachtal","zuechter":"Wladimir Handschuh" };{ "datum":"12.08.2022","rueden":2,"huendinnen":6,"vater":"Honeyhouse Guess Who Is At Ryediver","mutter":"Ch. Lower Saxon Asimbonanga","name":"Lower Saxon","zuechter":"Renate Hilger" };{ "datum":"15.09.2023","rueden":2,"huendinnen":4,"vater":"Ch. Victorious Attila King of Corgi vom Kalimandscharo","mutter":"Quest of Queen Arya vom Kalimandscharo","name":"vom Kalimandscharo","zuechter":"Nancy Leetz" };{ "datum":"23.04.2023","rueden":3,"huendinnen":5,"vater":"Amansi Sunshine For Me","mutter":"Sentinel Nairobi vom Kalimandscharo","name":"vom Kalimandscharo","zuechter":"Nancy Leetz" };{ "datum":"06.06.2024","rueden":1,"huendinnen":2,"vater":"Ch. Victoria Amatoria Rocky My Sweet","mutter":"Vanita Of The Jolly Pearls","name":"Dourin's","zuechter":"Rina Grouwstra" };{ "datum":"14.06.2023","rueden":3,"huendinnen":3,"vater":"Ch. Heym of Hassellyn Jumping Joseph Bob","mutter":"RyeDiver Clutch Cassidy","name":"RyeDiver","zuechter":"Olaf Schmidt" };{ "datum":"06.12.2022","rueden":2,"huendinnen":1,"vater":"Ch. Richard Valiant Knight For Massenbachtal","mutter":"Ch. Quo Vadis Olivia BOB","name":"Quo Vadis","zuechter":"Lilo Kiel" };{ "datum":"26.10.2023","rueden":2,"huendinnen":1,"vater":"Ch. Lagrein Alto Adige Iz Angarii","mutter":"Talisman Vasilisy Aurum","name":"from black riding Hood","zuechter":"Claudia Bohne" };{ "datum":"03.07.2024","rueden":2,"huendinnen":4,"vater":"Ch. Nebriowa The Full Monty","mutter":"Natsha Corgmanoff o'the Palatinate Pixies","name":"o'the Palatinate Pixies","zuechter":"Sabine Thomas" };{ "datum":"04.07.2024","rueden":2,"huendinnen":5,"vater":"Ch. Ginger Elf Peanut Butter At Borntobe","mutter":"Ch. Amoretka Lisiura","name":"Bakersfield","zuechter":"Marcus Wilke" };{ "datum":"04.06.2023","rueden":2,"huendinnen":2,"vater":"Oakwood Golden Glacé Chocolat","mutter":"Akswell Ya Euphoria","name":"Oakwood Golden","zuechter":"Gebkea Nieter" };{ "datum":"31.08.2022","rueden":0,"huendinnen":1,"vater":"Pumuckl vom Kalimandscharo","mutter":"Academia Canis Femme Fatale","name":"von Pfotenstolz","zuechter":"Myrjam Langen" };{ "datum":"15.05.2024","rueden":2,"huendinnen":1,"vater":"Ch. Victorious Attila King of Corgi vom Kalimandscharo","mutter":"Minerva McGonagall vom Kalimandscharo","name":"von der Müggelspree","zuechter":"Sigrid" };{ "datum":"06.06.2023","rueden":3,"huendinnen":3,"vater":"Karat I J Byrshtnovogo Kraju","mutter":"Vally von Kirchhellen","name":"von Kirchhellen","zuechter":"Johannes" };{ "datum":"06.06.2022","rueden":1,"huendinnen":0,"vater":"Ch. Greenwoods Secret Agent II","mutter":"Quality Mark Benediction Of Heavens","name":"Ellydan","zuechter":"Pia Immoor" };{ "datum":"10.05.2022","rueden":2,"huendinnen":4,"vater":"Ch. Daredevil's Hunting for Compliments from Staken","mutter":"Twenty Oaks Farm Conchita","name":"Twenty Oaks Farm","zuechter":"Astrid Rumprecht" };{ "datum":"01.05.2023","rueden":2,"huendinnen":4,"vater":"Ch. Daredevil's Hunting for Compliments from Staken","mutter":"Ch. Twenty Oaks Farm Caitlyn","name":"Twenty Oaks Farm","zuechter":"Astrid Rumprecht" };{ "datum":"19.05.2023","rueden":4,"huendinnen":4,"vater":"Amansi Sunshine For Me","mutter":"PR Little Royal Rascals Bridget Jones","name":"PR Little Royal Rascals","zuechter":"Patricia" };{ "datum":"07.06.2022","rueden":3,"huendinnen":2,"vater":"Ch. Pemcader Light My Fire","mutter":"Ch. Felicitas Bob vom Massenbachtal","name":"vom Massenbachtal","zuechter":"Wladimir Handschuh" };{ "datum":"04.05.2024","rueden":4,"huendinnen":2,"vater":"Limbonsnest Snowberry","mutter":"Syramiton Dream Amy","name":"Syramiton Dream","zuechter":"Sylvia" };{ "datum":"20.01.2024","rueden":1,"huendinnen":5,"vater":"Ch. Johnny I Hardly Knew Ya o'the Palatinate Pixies","mutter":"Ch. Double Creek Gossip Girl","name":"o'the Palatinate Pixies","zuechter":"Sabine Thomas" };{ "datum":"07.09.2023","rueden":3,"huendinnen":2,"vater":"Ch. Born To Be Glitter In The Air","mutter":"Bitch Royal from black riding Hood","name":"from scuffle Mouse","zuechter":"Cornelia Crantz" };{ "datum":"11.12.2021","rueden":2,"huendinnen":0,"vater":"Kingstone Iz Byrshtunovogo Kraju","mutter":"Davina Of The Jolly Jumpers","name":"Dourin's","zuechter":"Rina Grouwstra" };{ "datum":"06.08.2022","rueden":2,"huendinnen":2,"vater":"Heym of Hassellyn Irresistible Isidor","mutter":"All my lovin Aurelia from the Pegnitzfairys","name":"from the Pegnitzfairys","zuechter":"Ruth Schroetel" };{ "datum":"14.04.2024","rueden":1,"huendinnen":2,"vater":"Ch. Vuedor Sky Rocket","mutter":"Alice vom Jubachtal","name":"Höhle der Loewen","zuechter":"Jens" };{ "datum":"08.09.2023","rueden":1,"huendinnen":4,"vater":"Ch. Füchslein Fast And Furious o'the Palatinate Pixies","mutter":"Holla die Waldfee o'the Palatinate Pixies","name":"o'the Palatinate Pixies","zuechter":"Sabine Thomas" };{ "datum":"05.06.2024","rueden":4,"huendinnen":3,"vater":"Ch. Vuedor Sky Rocket","mutter":"Ch. Peek","name":"o'the Palatinate Pixies","zuechter":"Sabine Thomas" };{ "datum":"24.07.2023","rueden":2,"huendinnen":4,"vater":"Ch. Daredevil's Hunting for Compliments from Staken","mutter":"Daredevil's VALENTINE VAMPIRE from Staken","name":"Daredevil's...from Staken","zuechter":"Danny Reinkehr" };{ "datum":"11.04.2023","rueden":6,"huendinnen":5,"vater":"Ch. Andvol Marius Loo","mutter":"Andvol Chelsea Flowers","name":"Pemspride","zuechter":"Astrid Acht" };{ "datum":"29.04.2022","rueden":0,"huendinnen":1,"vater":"Quo Vadis Xandro BOB","mutter":"Ch. Pemspride Double Trouble","name":"Pemspride","zuechter":"Astrid Acht" };{ "datum":"08.01.2024","rueden":3,"huendinnen":5,"vater":"Ch. Daredevil's Macho Kiwi King from Staken","mutter":"Honeyhouse Party In The USA","name":"Bakersfield","zuechter":"Marcus Wilke" };{ "datum":"15.05.2023","rueden":3,"huendinnen":4,"vater":"Ch. Heavenli Lab Vincent For Massenbachtal","mutter":"Quo Vadis Ginny glamour Girl","name":"Quo Vadis","zuechter":"Lilo Kiel" };{ "datum":"07.06.2023","rueden":1,"huendinnen":5,"vater":"Ch. Heym of Hassellyn Jumping Joseph Bob","mutter":"Daredevil's No Rye Too High from Staken","name":"RyeDiver","zuechter":"Gloria Kiy" };{ "datum":"08.01.2023","rueden":2,"huendinnen":2,"vater":"Coco Jin Across the Desert","mutter":"Poem of Love to Carrie vom Kalimandscharo","name":"vom Kalimandscharo","zuechter":"Nancy Leetz" };{ "datum":"23.04.2023","rueden":0,"huendinnen":7,"vater":"Ch. Bart Junoba’s House","mutter":"Ch. Quo Vadis Wookie","name":"Quo Vadis","zuechter":"Lilo Kiel" };{ "datum":"06.03.2022","rueden":1,"huendinnen":1,"vater":"Ch. Nothing Compares 2U Halo Rudens Legendos","mutter":"Ch. Daredevil's Go Gentle from Staken","name":"Daredevil's...from Staken","zuechter":"Danny Reinkehr" };{ "datum":"19.03.2023","rueden":0,"huendinnen":2,"vater":"Percy Iz Doma Vengee","mutter":"Samoya Von Haus Vom Steraldted","name":"von Kirchhellen","zuechter":"Johannes" };{ "datum":"15.11.2021","rueden":2,"huendinnen":0,"vater":"Ch. Ermyn Sky of Stars","mutter":"Oakwood Golden Chips","name":"Oakwood Golden","zuechter":"Gebkea Nieter" };{ "datum":"07.04.2024","rueden":1,"huendinnen":2,"vater":"Ch. Vuedor Sky Rocket","mutter":"Alice vom Jubachtal","name":"Höhle der Loewen","zuechter":"Jens" };{ "datum":"01.04.2022","rueden":4,"huendinnen":6,"vater":"Karat Iz Byrshtunovogo Kraju","mutter":"Dourin’s Robine Pem BOB","name":"Dourin's","zuechter":"Rina Grouwstra" };{ "datum":"03.04.2022","rueden":5,"huendinnen":1,"vater":"Ch. Heavenli Lab Vincent For Massenbachtal","mutter":"Ch. Füchslein Frech o'the Palatinate Pixies","name":"von der Wertachau","zuechter":"Brigitte Stammel" };{ "datum":"06.02.2024","rueden":3,"huendinnen":2,"vater":"Ch. Heartbreaker Tri From Valhalos Sargas","mutter":"Quo Vadis Ginny glamour Girl","name":"Quo Vadis","zuechter":"Lilo Kiel" };{ "datum":"03.06.2023","rueden":1,"huendinnen":3,"vater":"Ch. Richard Valiant Knight For Massenbachtal","mutter":"Ch. Peek","name":"o'the Palatinate Pixies","zuechter":"Sabine Thomas" };{ "datum":"03.11.2022","rueden":3,"huendinnen":4,"vater":"Ch. Atsel Hof Mark","mutter":"Zensi von Kirchhellen","name":"Queenpaws","zuechter":"Lena Gerner" };{ "datum":"22.05.2023","rueden":1,"huendinnen":2,"vater":"Ch. Cornatello Apocalypse","mutter":"One for the Catwalk o'the Palatinate Pixies","name":"of the Western Saxon Highlanders","zuechter":"Dr. Berthold" };{ "datum":"07.10.2022","rueden":7,"huendinnen":3,"vater":"Inkery Line Zhusten For Pixies","mutter":"Natsha Corgmanoff o'the Palatinate Pixies","name":"o'the Palatinate Pixies","zuechter":"Sabine Thomas" };{ "datum":"02.01.2022","rueden":3,"huendinnen":2,"vater":"Ch. Jaro Little Fox vom Kalimandscharo","mutter":"Ch. Lady Sansa vom Kalimandscharo","name":"vom Kalimandscharo","zuechter":"Nancy Leetz" };{ "datum":"14.06.2023","rueden":1,"huendinnen":2,"vater":"Ch. Richard Valiant Knight For Massenbachtal","mutter":"Ch. Fleur Rebelle Veronika","name":"vonne Daggelküste","zuechter":"Gaby Hauber" };{ "datum":"22.08.2023","rueden":4,"huendinnen":4,"vater":"Pumuckl vom Kalimandscharo","mutter":"Aleant Divine Diva","name":"from the Pegnitzfairys","zuechter":"Ruth Schroetel" };{ "datum":"25.11.2022","rueden":4,"huendinnen":3,"vater":"Kalashnikhof Armani","mutter":"Savoy Von Haus Vom Steraldted","name":"von Kirchhellen","zuechter":"Johannes" };{ "datum":"18.08.2024","rueden":1,"huendinnen":0,"vater":"Egil Ellefolk o'the Palatinate Pixies","mutter":"Hulapalu von Pfotenstolz","name":"von Pfotenstolz","zuechter":"Myrjam Langen" };{ "datum":"17.11.2021","rueden":4,"huendinnen":3,"vater":"Ch. Victoria Amatoria Rocky My Sweet","mutter":"Grace Funny Beauty","name":"vom Old Tom","zuechter":"Jolanta Vogt" };{ "datum":"10.12.2022","rueden":0,"huendinnen":1,"vater":"Ch. Richard Valiant Knight For Massenbachtal","mutter":"Ch. Fleur Rebelle Veronika","name":"vom Massenbachtal","zuechter":"Wladimir Handschuh" };{ "datum":"14.06.2023","rueden":3,"huendinnen":3,"vater":"Ch. Heym of Hassellyn Jumping Joseph Bob","mutter":"RyeDiver Clutch Cassidy","name":"RyeDiver","zuechter":"Gloria Kiy" };{ "datum":"27.02.2023","rueden":4,"huendinnen":3,"vater":"Ch. Johnny I Hardly Knew Ya o'the Palatinate Pixies","mutter":"Ch. Shamquin Nsure Good Lovin","name":"o'the Palatinate Pixies","zuechter":"Sabine Thomas" };{ "datum":"17.11.2022","rueden":1,"huendinnen":1,"vater":"Kalashnikhof Armani","mutter":"Raja von Kirchhellen","name":"von Kirchhellen","zuechter":"Johannes" };{ "datum":"04.04.2023","rueden":3,"huendinnen":2,"vater":"Ch. Daredevil's Macho Kiwi King from Staken","mutter":"Talisman Vasilisy Aurum","name":"from black riding Hood","zuechter":"Claudia Bohne" };{ "datum":"20.12.2021","rueden":3,"huendinnen":4,"vater":"Aikemuno Zherar","mutter":"Samoya Von Haus Vom Steraldted","name":"von Kirchhellen","zuechter":"Johannes" };{ "datum":"09.07.2022","rueden":1,"huendinnen":0,"vater":"Ch. Vuedor Sky Rocket","mutter":"Ch. Mistycor Secret Look For Daredevil’s","name":"Daredevil's...from Staken","zuechter":"Danny Reinkehr" };{ "datum":"24.04.2023","rueden":1,"huendinnen":1,"vater":"Ch. Richard Valiant Knight For Massenbachtal","mutter":"Ch. Daredevil's Principally Prada from Staken","name":"Daredevil's...from Staken","zuechter":"Danny Reinkehr" };{ "datum":"09.06.2022","rueden":4,"huendinnen":4,"vater":"Kingston Iz Byrshtunovogo Kraju","mutter":"Uma Bob vom Old Tom","name":"Syramiton Dream","zuechter":"Sylvia" };{ "datum":"23.09.2023","rueden":5,"huendinnen":5,"vater":"Ch. Victoria Amatoria Ringo Starr","mutter":"Victoria Amatoria Samanta Fox","name":"von Pfotenstolz","zuechter":"Myrjam Langen" };{ "datum":"11.04.2022","rueden":5,"huendinnen":3,"vater":"Ch. Jean Luc PiCorg o'the Palatinate Pixies","mutter":"Holla die Waldfee o'the Palatinate Pixies","name":"o'the Palatinate Pixies","zuechter":"Sabine Thomas" };{ "datum":"27.08.2022","rueden":2,"huendinnen":2,"vater":"Good Luck Stone Edesiy","mutter":"Dourin’s Ivory Pem","name":"von Kirchhellen","zuechter":"Johannes" };{ "datum":"26.06.2023","rueden":3,"huendinnen":5,"vater":"Ch. Richard Valiant Knight For Massenbachtal","mutter":"Be Queen Dubensky Zamok","name":"von der Salzklinge","zuechter":"Harald Grünewald" };{ "datum":"17.07.2022","rueden":3,"huendinnen":1,"vater":"Ch. Greenwoods Secret Agent II","mutter":"Ch. Siggen’s J J Janis Joplin","name":"vonne Daggelküste","zuechter":"Gaby Hauber" };{ "datum":"01.05.2023","rueden":6,"huendinnen":3,"vater":"Ch. Richard Valiant Knight For Massenbachtal","mutter":"Ch. Eowyn vom Massenbachtal","name":"vom Massenbachtal","zuechter":"Wladimir Handschuh" };{ "datum":"05.07.2023","rueden":1,"huendinnen":3,"vater":"Honeyhouse Guess Who Is At Ryediver","mutter":"Ch. Daredevil's Q As A Button from Staken","name":"Rosegarden","zuechter":"Birgit" };{ "datum":"05.05.2022","rueden":4,"huendinnen":1,"vater":"Ch. Daredevil's Never Ever from Staken","mutter":"Ch. Just Jane Doe o'the Palatinate Pixies","name":"o'the Palatinate Pixies","zuechter":"Sabine Thomas" };{ "datum":"07.05.2023","rueden":5,"huendinnen":3,"vater":"Ch. Vuedor Sky Rocket","mutter":"Marvelous Mrs Maisel o'the Palatinate Pixies","name":"Oakwood Golden","zuechter":"Gebkea Nieter" };{ "datum":"27.04.2024","rueden":2,"huendinnen":2,"vater":"Ch. Johnny I Hardly Knew Ya o'the Palatinate Pixies","mutter":"Time To Bloom De Jaykay Land","name":"of the Western Saxon Highlanders","zuechter":"Dr. Berthold" };{ "datum":"17.09.2023","rueden":4,"huendinnen":2,"vater":"Kingston Iz Byrshtunovogo Kraju","mutter":"Uma Bob vom Old Tom","name":"Syramiton Dream","zuechter":"Sylvia" };{ "datum":"03.12.2022","rueden":1,"huendinnen":2,"vater":"Pumuckl vom Kalimandscharo","mutter":"Creme Brulee von Pfotenstolz","name":"vom Jubachtal","zuechter":"Matthias Schneider" };{ "datum":"07.06.2023","rueden":1,"huendinnen":5,"vater":"Ch. Heym of Hassellyn Jumping Joseph Bob","mutter":"Daredevil's No Rye Too High from Staken","name":"RyeDiver","zuechter":"Olaf Schmidt" };{ "datum":"10.12.2021","rueden":1,"huendinnen":2,"vater":"Aikemuno Zherar","mutter":"Freya von Kirchhellen","name":"von Kirchhellen","zuechter":"Johannes" };{ "datum":"27.04.2024","rueden":3,"huendinnen":2,"vater":"SGF Windswept Rumbling Thunder","mutter":"Ch. Syramiton Dream Abby","name":"Syramiton Dream","zuechter":"Sylvia" };